{"22": {"0": {"Atom 1": "(3,)", "Atom 2": "(26,)", "NMR exp": 3.19, "lower bound": 0.0, "upper bound": 3.5100000000000002, "md": [4.31152772857277]}, "1": {"Atom 1": "(3,)", "Atom 2": "(13, 14)", "NMR exp": 1.83, "lower bound": 0.0, "upper bound": 3.16, "md": [3.327069635094057, 2.5420640196164683]}, "2": {"Atom 1": "(22,)", "Atom 2": "(26,)", "NMR exp": 2.93, "lower bound": 0.0, "upper bound": 3.22, "md": [3.467011635657586]}, "3": {"Atom 1": "(19, 20)", "Atom 2": "(26,)", "NMR exp": 2.73, "lower bound": 0.0, "upper bound": 4.2700000000000005, "md": [3.145768297143527, 4.310736262728691]}, "4": {"Atom 1": "(16, 17)", "Atom 2": "(26,)", "NMR exp": 2.71, "lower bound": 0.0, "upper bound": 4.24, "md": [3.369140321373977, 4.708316256896649]}, "5": {"Atom 1": "(13, 14)", "Atom 2": "(26,)", "NMR exp": 2.63, "lower bound": 0.0, "upper bound": 4.14, "md": [3.082191200022109, 4.1765663560592365]}, "6": {"Atom 1": "(47,)", "Atom 2": "(59,)", "NMR exp": 2.57, "lower bound": 0.0, "upper bound": 2.83, "md": [3.5215994628173846]}, "7": {"Atom 1": "(49,)", "Atom 2": "(59,)", "NMR exp": 3.39, "lower bound": 0.0, "upper bound": 3.73, "md": [2.550594041614976]}, "8": {"Atom 1": "(61,)", "Atom 2": "(1,)", "NMR exp": 2.17, "lower bound": 0.0, "upper bound": 2.39, "md": [3.4546741255300115]}, "9": {"Atom 1": "(1,)", "Atom 2": "(3,)", "NMR exp": 2.6, "lower bound": 0.0, "upper bound": 2.86, "md": [2.9124441948213358]}, "10": {"Atom 1": "(1,)", "Atom 2": "(5, 6)", "NMR exp": 2.37, "lower bound": 0.0, "upper bound": 3.83, "md": [3.4826617973970913, 2.498616047886]}, "11": {"Atom 1": "(16, 17)", "Atom 2": "(13, 14)", "NMR exp": 1.73, "lower bound": 0.0, "upper bound": 4.19, "md": [2.3420885422905617, 2.7195478990532167, 2.943523786801388, 2.3382778781673963]}, "12": {"Atom 1": "(26,)", "Atom 2": "(28,)", "NMR exp": 2.31, "lower bound": 0.0, "upper bound": 2.54, "md": [2.942855456798783]}, "13": {"Atom 1": "(28,)", "Atom 2": "(35, 36, 37, 39, 40, 41)", "NMR exp": 3.23, "lower bound": 0.0, "upper bound": 6.99, "md": [3.0883905361435664, 3.0944155770287716, 3.102870405407868, 2.9192352782354773, 2.9080422172919027, 2.904885538330479]}, "14": {"Atom 1": "(45,)", "Atom 2": "(50,)", "NMR exp": 2.75, "lower bound": 0.0, "upper bound": 3.02, "md": [3.184968167487458]}, "15": {"Atom 1": "(45,)", "Atom 2": "(49,)", "NMR exp": 3.02, "lower bound": 0.0, "upper bound": 3.3200000000000003, "md": [3.027132598991603]}, "16": {"Atom 1": "(47,)", "Atom 2": "(50,)", "NMR exp": 2.2600000000000002, "lower bound": 0.0, "upper bound": 2.49, "md": [2.608157695344015]}, "17": {"Atom 1": "(47,)", "Atom 2": "(49,)", "NMR exp": 2.11, "lower bound": 0.0, "upper bound": 2.32, "md": [2.5858543752226733]}, "18": {"Atom 1": "(50,)", "Atom 2": "(54, 55)", "NMR exp": 2.6, "lower bound": 0.0, "upper bound": 6.0600000000000005, "md": [3.650186326810618, 2.449145493152302]}, "19": {"Atom 1": "(49,)", "Atom 2": "(54, 55)", "NMR exp": 3.31, "lower bound": 0.0, "upper bound": 7.11, "md": [3.7282824419219254, 2.590367538525684]}, "20": {"Atom 1": "(59,)", "Atom 2": "(63, 64)", "NMR exp": 2.49, "lower bound": 0.0, "upper bound": 3.98, "md": [2.774201521385065, 3.018245790914972]}, "21": {"Atom 1": "(61,)", "Atom 2": "(63, 64)", "NMR exp": 2.08, "lower bound": 0.0, "upper bound": 3.47, "md": [2.582756669011066, 2.4243087775458627]}}}